filestorages/__init__.py
django_filestorages-0.1.dist-info/LICENSE
django_filestorages-0.1.dist-info/METADATA
django_filestorages-0.1.dist-info/WHEEL
django_filestorages-0.1.dist-info/top_level.txt
django_filestorages-0.1.dist-info/RECORD
