Metadata-Version: 2.1
Name: django-filestorages
Version: 0.1
Summary: Configurable file storages for Django
Home-page: https://github.com/rczajka/django-filestorages
Author: Radek Czajka
Author-email: rczajka@rczajka.pl
License: UNKNOWN
Platform: UNKNOWN
Classifier: Programming Language :: Python :: 2
Classifier: Programming Language :: Python :: 3
Classifier: License :: OSI Approved :: MIT License
Classifier: Operating System :: OS Independent
Requires-Dist: Django
